nornir_max_inventory/__init__.py
nornir_max_inventory/plugins/inventory/__init__.py
nornir_max_inventory/plugins/inventory/table.py
nornir_max_inventory-0.1.0.dist-info/entry_points.txt
nornir_max_inventory-0.1.0.dist-info/LICENSE
nornir_max_inventory-0.1.0.dist-info/METADATA
nornir_max_inventory-0.1.0.dist-info/WHEEL
nornir_max_inventory-0.1.0.dist-info/RECORD
