Metadata-Version: 2.3
Name: nornir_max_inventory
Version: 0.1.0
Summary: 测试用，作为Nornir的inventory 插件管理设备对象。依赖版本改为新版本。
License: Apache-2.0
Author: luis330
Author-email: luis@freeba.org
Requires-Python: >=3.10.0,<4.0.0
Classifier: License :: OSI Approved :: Apache Software License
Classifier: Programming Language :: Python :: 3
Classifier: Programming Language :: Python :: 3.10
Classifier: Programming Language :: Python :: 3.11
Classifier: Programming Language :: Python :: 3.12
Classifier: Programming Language :: Python :: 3.13
Requires-Dist: nornir (>=3.5.0,<4.0.0)
Requires-Dist: pandas (>=2.2.3,<3.0.0)
